{
    "branches": {
        "BocaRatonFL": {
            "id": "BocaRatonFL",
            "links": [
                "https://www.facebook.com/groups/RBE.USA.FL.BocaRaton/"
            ],
            "name": "Boca Raton, FL"
        },
        "BonitaSpringsFL": {
            "id": "BonitaSpringsFL",
            "links": [
                "http://fb.me/TZMFL06SW",
                "www.facebook.com/groups/ZeitgeistSouthwestFloridaChapter/",
                "https://www.facebook.com/groups/RBE.USA.FL.BonitaSprings/"
            ],
            "name": "Bonita Springs, FL",
            "subname": "bonita-springs"
        },
        "BoyntonBeachFL": {
            "id": "BoyntonBeachFL",
            "links": [
                "https://www.facebook.com/groups/RBE.USA.FL.BoyntonBeach/"
            ],
            "name": "Boynton Beach, FL"
        },
        "CapeCoral": {
            "id": "CapeCoral",
            "links": [
                "http://fb.me/TZMFL06SW",
                "www.facebook.com/groups/ZeitgeistSouthwestFloridaChapter/",
                "https://www.facebook.com/groups/RBE.USA.FL.CapeCoral/"
            ],
            "name": "Cape Coral",
            "subname": "cape-coral"
        },
        "ClearwaterFL": {
            "id": "ClearwaterFL",
            "links": [
                "http://fb.me/ZMFL05CW",
                "https://www.facebook.com/groups/RBE.USA.FL.Clearwater/"
            ],
            "name": "Central West Florida Regional Sub-Chapter",
            "subname": "clearwater"
        },
        "DaytonaFL": {
            "id": "DaytonaFL",
            "links": [
                "http://fb.me/TZMFL04C",
                "https://www.facebook.com/groups/RBE.USA.FL.Daytona/"
            ],
            "name": "Central Florida Regional Sub-Chapter",
            "subname": "daytona"
        },
        "Ft.Lauderdale": {
            "id": "Ft.Lauderdale",
            "links": [
                "https://www.facebook.com/fortlauderdalezm/",
                "https://www.facebook.com/groups/RBE.USA.FL.FtLauderdale/"
            ],
            "name": "Ft. Lauderdale"
        },
        "Ft.MyersFL": {
            "id": "Ft.MyersFL",
            "links": [
                "https://www.facebook.com/groups/RBE.USA.FL.FtMyers/",
                "http://fb.me/TZMFL06SW",
                "www.facebook.com/groups/ZeitgeistSouthwestFloridaChapter/",
                "Ft. Myers, FL"
            ],
            "name": "Ft. Myers, FL",
            "subname": "ft-myers"
        },
        "GainesvilleFL": {
            "id": "GainesvilleFL",
            "links": [
                "https://www.facebook.com/groups/RBE.USA.FL.Gainesville/"
            ],
            "name": "Gainesville, FL"
        },
        "HollywoodFL": {
            "id": "HollywoodFL",
            "links": [
                "https://www.facebook.com/groups/RBE.USA.FL.Hollywood/"
            ],
            "name": "Hollywood, FL"
        },
        "JacksonvilleFL": {
            "id": "JacksonvilleFL",
            "links": [
                "https://www.facebook.com/groups/RBE.USA.FL.Jacksonville/"
            ],
            "name": "Jacksonville, FL"
        },
        "Melbourne": {
            "id": "Melbourne",
            "links": [
                "http://fb.me/TZMFL04C",
                "https://www.facebook.com/groups/RBE.USA.FL.Melbourne/"
            ],
            "name": "Central Florida Regional Sub-Chapter",
            "subname": "melbourne"
        },
        "MiamiFL": {
            "id": "MiamiFL",
            "links": [
                "https://www.facebook.com/groups/RBE.USA.FL.Miami/"
            ],
            "name": "Miami, FL"
        },
        "NaplesFL": {
            "id": "NaplesFL",
            "links": [
                "http://fb.me/TZMFL06SW",
                "www.facebook.com/groups/ZeitgeistSouthwestFloridaChapter/",
                "https://www.facebook.com/groups/RBE.USA.FL.Naples"
            ],
            "name": "Naples, FL",
            "subname": "naples"
        },
        "OrlandoFL": {
            "id": "OrlandoFL",
            "links": [
                "http://fb.me/TZMFL04C",
                "https://www.facebook.com/groups/RBE.USA.FL.Orlando/"
            ],
            "name": "Central Florida Regional Sub-Chapter",
            "subname": "orlando"
        },
        "PanamaCityFL": {
            "id": "PanamaCityFL",
            "links": [
                "North West Florida Regional Sub-Chapter",
                "http://fb.me/TZMFL01NW/",
                "Panama City, FL",
                "https://www.facebook.com/groups/RBE.USA.FL.PanamaCity/"
            ],
            "name": "North West Florida Regional Sub-ChapterNorth West Florida Regional Sub-Chapter",
            "subname": "panama-city"
        },
        "PensacolaFL": {
            "id": "PensacolaFL",
            "links": [
                "North West Florida Regional Sub-Chapter",
                "http://fb.me/TZMFL01NW/",
                "Pensacola, FL",
                "https://www.facebook.com/groups/RBE.USA.FL.Pensacola/"
            ],
            "name": "North West Florida Regional Sub-ChapterNorth West Florida Regional Sub-Chapter",
            "subname": "pensacola"
        },
        "PompanoFL": {
            "id": "PompanoFL",
            "links": [
                "https://www.facebook.com/groups/RBE.USA.FL.Pompano/"
            ],
            "name": "Pompano, FL"
        },
        "PortSt.LucyFL": {
            "id": "PortSt.LucyFL",
            "links": [
                "https://www.facebook.com/groups/RBE.USA.FL.PtStLucie/"
            ],
            "name": "Port St. Lucy, FL"
        },
        "SeminoleFL": {
            "id": "SeminoleFL",
            "links": [
                "http://fb.me/ZMFL05CW",
                "https://www.facebook.com/groups/RBE.USA.FL.Seminole/"
            ],
            "name": "Central West Florida Regional Sub-Chapter",
            "subname": "seminole"
        },
        "SouthwestGroup:": {
            "id": "SouthwestGroup:",
            "links": [],
            "name": "Southwest Group:"
        },
        "SpringHillFL": {
            "id": "SpringHillFL",
            "links": [
                "http://fb.me/ZMFL05CW",
                "https://www.facebook.com/groups/RBE.USA.FL.SpringHill/"
            ],
            "name": "Central West Florida Regional Sub-Chapter",
            "subname": "spring-hill"
        },
        "St.PetersburgFL": {
            "id": "St.PetersburgFL",
            "links": [
                "http://fb.me/ZMFL05CW",
                "https://www.facebook.com/groups/TZMStPeteFL/",
                "Corey Grandmaison"
            ],
            "name": "Central West Florida Regional Sub-Chapter",
            "subname": "st-petersburg"
        },
        "TZMFL01NW": {
            "id": "TZMFL01NW",
            "links": [
                "http://fb.me/TZMFL01NW/"
            ],
            "name": "North West Florida Regional Chapter"
        },
        "TZMFL02NC": {
            "id": "TZMFL02NC",
            "links": [
                "http://fb.me/TZMFL02NC"
            ],
            "name": "North Central Florida Regional Chapter"
        },
        "TZMFL03NE": {
            "id": "TZMFL03NE",
            "links": [
                "http://fb.me/TZMFL03NE/"
            ],
            "name": "North East Florida Regional Chapter"
        },
        "TZMFL04C": {
            "id": "TZMFL04C",
            "links": [
                "http://fb.me/TZMFL04C"
            ],
            "name": "Central Florida Regional Chapter"
        },
        "TZMFL06SW": {
            "id": "TZMFL06SW",
            "links": [
                "http://fb.me/TZMFL06SW"
            ],
            "name": "South West Florida Regional Chapter"
        },
        "TZMFL07SE": {
            "id": "TZMFL07SE",
            "links": [
                "http://fb.me/TZMFL07SE/"
            ],
            "name": "South East Florida Regional Chapter"
        },
        "TallahasseeFL": {
            "id": "TallahasseeFL",
            "links": [
                "http://fb.me/TZMFL02NC",
                "https://www.facebook.com/groups/RBE.USA.FL.Talahassee/",
                "https://www.facebook.com/groups/RBE.USA.FL.Tallahassee/"
            ],
            "name": "North Central Florida Regional Sub-Chapter",
            "subname": "tallahassee"
        },
        "TampaFL": {
            "id": "TampaFL",
            "links": [
                "http://fb.me/ZMFL05CW",
                "https://www.facebook.com/groups/148406091868787/"
            ],
            "name": "Central West Florida Regional Sub-Chapter",
            "subname": "tampa"
        },
        "WestPalmBeachFL": {
            "id": "WestPalmBeachFL",
            "links": [
                "https://www.facebook.com/groups/RBE.USA.FL.WestPalmBeach"
            ],
            "name": "West Palm Beach, FL"
        },
        "ZMFL05CW": {
            "id": "ZMFL05CW",
            "links": [
                "http://fb.me/ZMFL05CW"
            ],
            "name": "Central West Florida Regional Chapter"
        },
        "ch-algeria": {
            "Country": "Algeria",
            "Email": "N/A",
            "Facebook": "https://www.facebook.com/zeitgeistdz/",
            "Last Known Event": "Unknown",
            "Last Update": "01/03/2019",
            "People": "N/A",
            "Started": "Unknown",
            "Status": "Defunct",
            "Website": "https://zeitgeistdz.wordpress.com",
            "id": "ch-algeria",
            "website.feed.url": "https://zeitgeistdz.wordpress.com/feed.xml",
            "website.tested": "2020-06-02",
            "website.tested.datetime": "2020-06-02 15:55:21",
            "website.working": "true"
        },
        "ch-australia": {
            "Country": "Australia",
            "Email": "mailto:admin@zeitgeistaustralia.org",
            "Facebook": "https://www.facebook.com/groups/1257205007663030/about/",
            "Last Known Event": "Unknown",
            "Last Update": "04/02/2019",
            "People": "N/A",
            "Started": "Unknown",
            "Status": "Unknown",
            "Twitter": "https://twitter.com/TZMau",
            "Website": "http://www.zeitgeistaustralia.org/",
            "YouTube": "https://www.youtube.com/user/TZMAustralia",
            "id": "ch-australia",
            "website.feed.url": "https://www.zeitgeistaustralia.org/rss/",
            "website.tested": "2020-06-02",
            "website.tested.datetime": "2020-06-02 15:55:31",
            "website.working": "true"
        },
        "ch-austria": {
            "Country": "Austria",
            "Email": "N/A",
            "Facebook": "https://www.facebook.com/Die-Zeitgeist-Bewegung-Wien-1110526108965599/",
            "Last Known Event": "Zeitgeist Bewegung \u00d6sterreich auf der Veganmania Wien 2018",
            "Last Update": "04/02/2019",
            "People": "c.5-10",
            "Started": "11/10/2008",
            "Status": "Inactive",
            "Website": "N/A",
            "YouTube": "https://www.youtube.com/channel/UCnXI8lomfIA5r4cgSR9SUrg",
            "id": "ch-austria"
        },
        "ch-belgium": {
            "Country": "Belgium",
            "Email": "N/A",
            "Facebook": "https://www.facebook.com/pg/thezeitgeistmovementbelgium/",
            "Last Known Event": "Z-Day 2015 @ Ghent",
            "Last Update": "01/03/2019",
            "People": "N/A",
            "Started": "Unknown",
            "Status": "Inactive",
            "Website": "https://www.thezeitgeistmovement.be/",
            "id": "ch-belgium",
            "website.tested": "2020-06-02",
            "website.tested.datetime": "2020-06-03 11:12:53",
            "website.working": "true"
        },
        "ch-brazil": {
            "Country": "Brazil",
            "Email": "N/A",
            "Facebook": "https://www.facebook.com/groups/zeitgeistbrasil/",
            "Last Known Event": "Unknown",
            "Last Update": "01/03/2019",
            "People": "N/A",
            "Started": "28/06/2011",
            "Status": "Active",
            "Website": "http://www.mzbr.com.br/",
            "id": "ch-brazil",
            "website.tested": "2020-06-02",
            "website.tested.datetime": "2020-06-02 15:59:19",
            "website.working": "false"
        },
        "ch-bulgaria": {
            "Country": "Bulgaria",
            "Email": "N/A",
            "Facebook": "https://www.facebook.com/ZeitgeistBulgaria-1631514600435748/",
            "Last Known Event": "Unknown",
            "Last Update": "01/03/2019",
            "People": "N/A",
            "Started": "c.2008",
            "Status": "Unknown",
            "Website": "www.thezeitgeistmovement.bg/",
            "id": "ch-bulgaria",
            "website.tested": "2020-06-02",
            "website.tested.datetime": "2020-06-02 15:59:19",
            "website.working": "false"
        },
        "ch-canada": {
            "Country": "Canada",
            "Email": "N/A",
            "Facebook": "https://www.facebook.com/Zeitgeist-Canada-157145994349890/",
            "Facebook Group": "https://www.facebook.com/groups/107839678444//",
            "Last Known Event": "Unknown",
            "Last Update": "01/03/2019",
            "People": "c.20",
            "Started": "2008",
            "Status": "Active",
            "Website": "http://www.zeitgeistcanada.ca/",
            "id": "ch-canada",
            "website.tested": "2020-06-02",
            "website.tested.datetime": "2020-06-02 15:59:19",
            "website.working": "false"
        },
        "ch-chile": {
            "Country": "Chile",
            "Email": "N/A",
            "Facebook": "https://www.facebook.com/TZMChile",
            "Facebook Group": "https://www.facebook.com/groups/tzmchile/",
            "Last Known Event": "Unknown",
            "Last Update": "01/03/2019",
            "People": "N/A",
            "Started": "Unknown",
            "Status": "Defunct",
            "Twitter": "https://twitter.com/TZMChile",
            "Website": "http://zchile.cl",
            "YouTube": "https://www.youtube.com/user/TZMChileOficial",
            "id": "ch-chile",
            "website.tested": "2020-06-02",
            "website.tested.datetime": "2020-06-02 15:59:19",
            "website.working": "false"
        },
        "ch-china": {
            "Country": "China",
            "Email": "tzm.in.china(at)gmail.com",
            "Last Known Event": "Unknown",
            "Last Update": "01/03/2019",
            "People": "N/A",
            "Started": "Unknown",
            "Status": "Unknown",
            "Website": "http://zmcn.org",
            "id": "ch-china",
            "website.tested": "2020-06-02",
            "website.tested.datetime": "2020-06-02 15:59:19",
            "website.working": "false"
        },
        "ch-costarica": {
            "Country": "Costa Rica",
            "Email": "zeitgeistcostarica(at)gmail.com",
            "Facebook": "https://www.facebook.com/MovimientoZeitgeistCostaRica/",
            "Facebook Group": "https://www.facebook.com/groups/166997563376064/",
            "Last Known Event": "Unknown",
            "Last Update": "01/03/2019",
            "People": "N/A",
            "Started": "Unknown",
            "Status": "Defunct",
            "Twitter": "https://twitter.com/zeitgeistcr",
            "Vimeo": "https://vimeo.com/channels/380525",
            "Website": "https://bienvenidosazeitgeistcostarica.blogspot.com/",
            "Website Blog": "https://zeitgeistcostarica.blogspot.com/",
            "id": "ch-costarica",
            "website.feed.url": "https://bienvenidosazeitgeistcostarica.blogspot.com/rss.xml",
            "website.tested": "2020-06-02",
            "website.tested.datetime": "2020-06-02 15:55:38",
            "website.working": "true"
        },
        "ch-czechrepublic": {
            "Country": "Czech Republic",
            "Email": "info(at)zeitgeistmovement.cz",
            "Facebook": "https://www.facebook.com/zeitgeistmovement.cz/",
            "Last Known Event": "Setk\u00e1n\u00ed \u010dlen\u016f, p\u0159\u00edznivc\u016f a sympatizant\u016f Hnut\u00ed Zeitgeist",
            "Last Update": "01/03/2019",
            "People": "N/A",
            "RSS": "https://www.zeitgeistmovement.cz/feed/",
            "Skype": "TZMczech",
            "Started": "c.2008",
            "Status": "Active",
            "Website": "https://www.zeitgeistmovement.cz",
            "YouTube": "https://www.youtube.com/user/TZMCzech/",
            "id": "ch-czechrepublic",
            "website.feed.url": "https://www.zeitgeistmovement.cz/rss/",
            "website.tested": "2020-06-02",
            "website.tested.datetime": "2020-06-02 15:55:42",
            "website.working": "true"
        },
        "ch-denmark": {
            "Country": "Denmark",
            "Email": "N/A",
            "Facebook": "https://www.facebook.com/tzmdk/",
            "Last Known Event": "Grav\u00f8l - Jacque Fresco (02/06/2017)",
            "Last Update": "04/02/2019",
            "People": "c.7",
            "Started": "11/10/2008",
            "Status": "Defunct",
            "Twitter": "https://twitter.com/Zeitgeist_DK",
            "Website": "https://www.thezeitgeistmovement.dk",
            "id": "ch-denmark",
            "website.tested": "2020-06-02",
            "website.tested.datetime": "2020-06-02 15:59:19",
            "website.working": "false"
        },
        "ch-ecuador": {
            "Country": "Ecuador",
            "Email": "N/A",
            "Facebook": "https://www.facebook.com/zecuadorcom/",
            "Facebook Group": "https://www.facebook.com/groups/71398663577/",
            "Last Known Event": "Unknown",
            "Last Update": "11/03/2019",
            "People": "N/A",
            "Started": "Unknown",
            "Status": "Defunct",
            "Website": "http://www.zecuador.com/",
            "YouTube": "https://www.youtube.com/user/Zecuadorcom/",
            "id": "ch-ecuador",
            "website.tested": "2020-06-02",
            "website.tested.datetime": "2020-06-02 15:59:19",
            "website.working": "false"
        },
        "ch-finland": {
            "Country": "Finland",
            "Email": "mailto:zeitgeistfinland@gmail.com",
            "Facebook": "https://www.facebook.com/ZeitgeistSuomi/",
            "Last Known Event": "N/A",
            "Last Update": "04/02/2019",
            "People": "c.15",
            "Started": "11/10/2008",
            "Status": "Active",
            "Website": "http://www.zeitgeist.fi/",
            "YouTube": "https://www.youtube.com/user/Zeitgeistliike",
            "id": "ch-finland",
            "website.feed.url": "https://www.zeitgeist.fi/feed.xml",
            "website.tested": "2020-06-02",
            "website.tested.datetime": "2020-06-02 15:55:42",
            "website.working": "true"
        },
        "ch-france": {
            "Country": "France",
            "Email": "mailto:contact@mouvement-zeitgeist.fr",
            "Facebook": "https://www.facebook.com/TZMFrancophone/",
            "Last Known Event": "Unknown",
            "Last Update": "05/02/2019",
            "People": "N/A",
            "Started": "11/10/2008",
            "Status": "Defunct",
            "Website": "http://mouvement-zeitgeist.fr/",
            "YouTube": "https://www.youtube.com/user/TZMFrancophone",
            "id": "ch-france",
            "website.tested": "2020-06-02",
            "website.tested.datetime": "2020-06-02 15:59:20",
            "website.working": "false"
        },
        "ch-germany": {
            "Country": "Germany",
            "Email": "mailto:info@tzm-stuttgart.de",
            "Facebook": "https://www.facebook.com/ZeitgeistMuenster",
            "Facebook Group": "https://www.facebook.com/groups/zeitgeistmovementproject/",
            "Last Known Event": "Unknown",
            "Last Update": "12/03/2019",
            "Newsletter": "https://docs.google.com/forms/d/e/1FAIpQLSchuW_sRk4Hv_7EAuCZRITq6MH7eONWTul-k7f6dA2o1YtoKg/viewform?c=0&w=1",
            "People": "c.10",
            "Started": "05/12/2012",
            "Status": "Active",
            "Website": "http://tzm-stuttgart.de/main/index.html",
            "YouTube": "https://www.youtube.com/channel/UC-Ccn6VatOWo6D2GZP5qDXw",
            "id": "ch-germany",
            "website.tested": "2020-06-02",
            "website.tested.datetime": "2020-06-02 15:59:20",
            "website.working": "false"
        },
        "ch-greece": {
            "Country": "Greece",
            "Email": "mailto:info@tzm.gr",
            "Facebook": "https://www.facebook.com/TheZeitgeistMovementGreece/",
            "Last Known Event": "\u0394\u03b9\u03b1\u03b4\u03b9\u03ba\u03c4\u03c5\u03b1\u03ba\u03ae \u03a3\u03c5\u03bd\u03ac\u03bd\u03c4\u03b7\u03c3\u03b7 \u0395\u03bb\u03bb\u03b7\u03bd\u03b9\u03ba\u03bf\u03cd \u03a4\u03bc\u03ae\u03bc\u03b1\u03c4\u03bf\u03c2 (15/02/2016)",
            "Last Update": "13/03/2019",
            "People": "N/A",
            "Started": "c.2008",
            "Status": "Defunct",
            "Twitter": "https://twitter.com/TZMGR",
            "Website": "https://zeitgeistmovement.gr/",
            "YouTube": "https://www.youtube.com/user/tzmgr",
            "id": "ch-greece",
            "website.tested": "2020-06-02",
            "website.tested.datetime": "2020-06-03 11:12:55",
            "website.working": "true"
        },
        "ch-guatemala": {
            "Country": "Guatemala",
            "Email": "mailto:contacto@zeitgeistguatemala.com",
            "Facebook": "https://www.facebook.com/ZeitgeistGuatemala/",
            "Last Known Event": "Unknown",
            "Last Update": "05/02/2019",
            "People": "N/A",
            "Started": "2012",
            "Status": "Defunct",
            "Website": "http://www.zeitgeistguatemala.com/",
            "id": "ch-guatemala",
            "website.tested": "2020-06-02",
            "website.tested.datetime": "2020-06-02 15:59:21",
            "website.working": "false"
        },
        "ch-hungary": {
            "Country": "Hungary",
            "Email": "tzmhungary(at)gmail.com",
            "Facebook": "https://www.facebook.com/tzmmagyarorszag/",
            "Facebook Group": "https://www.facebook.com/groups/792720950841508/",
            "Last Known Event": "II. Fenntarthat\u00f3s\u00e1gi szakmai konferencia",
            "Last Update": "01/03/2019",
            "People": "N/A",
            "Started": "11/10/2008",
            "Status": "Active",
            "Twitter": "https://twitter.com/tzmhungary",
            "Website": "http://tzm.hu/",
            "YouTube": "https://www.youtube.com/channel/UCcZE8Q_vRwzkJCJrImbyFrg",
            "id": "ch-hungary",
            "website.feed.url": "https://tzm.hu/rss/",
            "website.tested": "2020-06-02",
            "website.tested.datetime": "2020-06-02 15:55:52",
            "website.working": "true"
        },
        "ch-iceland": {
            "Country": "Iceland",
            "Email": "mailto:info@zeitgeistmovement.is",
            "Facebook": "https://www.facebook.com/tzmiceland/",
            "Last Known Event": "Zeitgeist-Dagur 2018",
            "Last Update": "03/02/2019",
            "People": "c.10",
            "Started": "11/10/2017",
            "Status": "Active",
            "Website": "https://www.zeitgeistmovement.is",
            "id": "ch-iceland",
            "website.tested": "2020-06-02",
            "website.tested.datetime": "2020-06-02 15:59:21",
            "website.working": "false"
        },
        "ch-india": {
            "Country": "India",
            "Email": "info(at)tzmindia.com (INACTIVE)",
            "Facebook": "https://www.facebook.com/TZMIndia/",
            "Google Forum": "https://groups.google.com/forum/#!forum/tzmindia",
            "Last Known Event": "Unknown",
            "Last Update": "11/03/2019",
            "People": "N/A",
            "Started": "Unknown",
            "Status": "Unknown",
            "Twitter": "https://twitter.com/tzmindia",
            "Website": "http://tzmindia.com/",
            "YouTube": "https://www.youtube.com/user/tzmindia",
            "id": "ch-india",
            "website.tested": "2020-06-02",
            "website.tested.datetime": "2020-06-02 15:59:22",
            "website.working": "false"
        },
        "ch-ireland": {
            "Country": "Ireland",
            "Email": "zeitgeistmovementireland(at)gmail.com(UNSURE IF MAINTAINED)",
            "Facebook": "https://www.facebook.com/zeitgeist.ireland",
            "Facebook Group": "https://www.facebook.com/groups/671187052927955/",
            "Last Known Event": "Unknown",
            "Last Update": "11/03/2019",
            "People": "N/A",
            "Started": "Unknown",
            "Status": "Defunct",
            "Website": "http://www.thezeitgeistmovement.ie/",
            "YouTube": "https://www.youtube.com/user/zeitgeistirelandtv",
            "id": "ch-ireland",
            "website.tested": "2020-06-02",
            "website.tested.datetime": "2020-06-02 15:59:22",
            "website.working": "false"
        },
        "ch-italy": {
            "Country": "Italy",
            "Email": "N/A",
            "Facebook": "https://www.facebook.com/movimentozeitgeist/",
            "Facebook Group": "https://www.facebook.com/groups/TZMviterbo/",
            "Flickr": "https://www.flickr.com/photos/zeitgeistitalia",
            "Last Known Event": "Unknown",
            "Last Update": "11/03/2019",
            "People": "N/A",
            "Started": "2018",
            "Status": "Active",
            "Twitter": "https://twitter.com/zeitgeistitalia",
            "Website": "http://www.zeitgeistitalia.org/",
            "YouTube": "https://www.youtube.com/user/Zeitgeistitalia/",
            "id": "ch-italy",
            "website.feed.url": "https://www.zeitgeistitalia.org/rss.xml",
            "website.tested": "2020-06-02",
            "website.tested.datetime": "2020-06-02 15:55:59",
            "website.working": "true"
        },
        "ch-japan": {
            "Country": "Japan",
            "Email": "N/A",
            "Facebook": "https://ja-jp.facebook.com/pg/tzmjapan/",
            "People": "N/A",
            "Restarted": "10/01/2019",
            "Started": "11/10/2008",
            "Status": "Developing",
            "Website": "zmjp.net",
            "https": "//ja-jp.facebook.com/pg/tzmjapan/",
            "id": "ch-japan",
            "website.tested": "2020-06-02",
            "website.tested.datetime": "2020-06-02 16:01:33",
            "website.working": "false"
        },
        "ch-kazakhstan": {
            "Country": "Kazakhstan",
            "Email": "N/A",
            "Facebook": "https://www.facebook.com/tzmkazakhstan/",
            "Last Known Event": "Unknown",
            "Last Update": "06/04/2019",
            "People": "N/A",
            "Started": "Unknown",
            "Status": "Defunct",
            "Trello": "https://trello.com/b/HERr3dxq/tzm-kazakhstan",
            "Twitter": "https://twitter.com/TZMkz",
            "Website": "N/A",
            "YouTube": "https://www.youtube.com/user/TZMKazakhstan",
            "id": "ch-kazakhstan"
        },
        "ch-latvia": {
            "Country": "Latvia",
            "Email": "N/A",
            "Facebook": "https://www.facebook.com/ZeitgeistLatvia/",
            "Facebook Group": "https://www.facebook.com/groups/523111318176212/",
            "Last Known Event": "N/A",
            "Last Update": "13/03/2019",
            "People": "2",
            "Started": "01/21/2019",
            "Status": "Developing",
            "Website": "N/A",
            "id": "ch-latvia"
        },
        "ch-malaysia": {
            "Country": "Malaysia",
            "Email": "N/A",
            "Facebook": "https://www.facebook.com/tzmmalaysia/",
            "Last Known Event": "Unknown",
            "Last Update": "05/02/2019",
            "People": "N/A",
            "Started": "06/10/2010",
            "Status": "Defunct",
            "Website": "N/A",
            "id": "ch-malaysia"
        },
        "ch-mexico": {
            "Country": "Mexico",
            "Email": "contacto(at)zeitgeist.com.mx (INACTIVE)",
            "Facebook": "https://www.facebook.com/TZMMEXICOOFICIAL",
            "Last Known Event": "Unknown",
            "Last Update": "11/03/2019",
            "People": "N/A",
            "Started": "c.2008",
            "Status": "Active",
            "Trello": "https://trello.com/board/capitulos-de-mexico/4fe25c11f9f166271d140912",
            "Twitter": "https://twitter.com/zmexico",
            "Website": "http://www.zeitgeist.com.mx/",
            "YouTube": "https://www.youtube.com/emzmexico",
            "id": "ch-mexico",
            "website.tested": "2020-06-02",
            "website.tested.datetime": "2020-06-02 16:01:34",
            "website.working": "false"
        },
        "ch-netherlands": {
            "Country": "Netherlands",
            "Email": "mailto:info@zeitgeistbeweging.nl",
            "Facebook": "https://www.facebook.com/zeitgeistbeweging/",
            "Facebook Group": "https://www.facebook.com/groups/zeitgeistbeweging",
            "Google+": "https://plus.google.com/+ZeitgeistbewegingNL",
            "Last Known Event": "Z-DAY 2017",
            "Last Update": "05/02/2019",
            "People": "c.10",
            "Started": "11/10/2017",
            "Status": "Inactive",
            "Twitter": "https://twitter.com/TZM_NL",
            "Website": "https://www.zeitgeistbeweging.nl/",
            "YouTube": "https://www.youtube.com/c/ZeitgeistbewegingNL",
            "id": "ch-netherlands",
            "website.tested": "2020-06-02",
            "website.tested.datetime": "2020-06-03 11:13:02",
            "website.working": "true"
        },
        "ch-norway": {
            "Country": "Norway",
            "Email": "N/A",
            "Facebook": "https://www.facebook.com/tzmnorway/",
            "Last Known Event": "N/A",
            "Last Update": "04/02/2019",
            "People": "N/A",
            "Restarted": "11/2018",
            "Started": "11/10/2008",
            "Status": "Developing",
            "Website": "https://www.zeitgeistbevegelsen.no",
            "id": "ch-norway",
            "website.tested": "2020-06-02",
            "website.tested.datetime": "2020-06-02 16:01:40",
            "website.working": "false"
        },
        "ch-paraguay": {
            "Country": "Paraguay",
            "Email": "mailto:boxmail2005@gmail.com",
            "Facebook": "https://www.facebook.com/TZMParaguayOficial/",
            "Last Known Event": "Unknown",
            "Last Update": "11/03/2019",
            "People": "N/A",
            "Started": "Unknown",
            "Status": "Defunct",
            "Website": "http://www.zeitgeistlatino.org",
            "id": "ch-paraguay",
            "website.tested": "2020-06-02",
            "website.tested.datetime": "2020-06-02 16:01:40",
            "website.working": "false"
        },
        "ch-philippines": {
            "Country": "Philippines",
            "Email": "support@tzmpilipinas.com (UNSURE IF ACTIVE)",
            "Facebook": "https://www.facebook.com/groups/tzmph/",
            "Facebook Group": "https://www.facebook.com/groups/tzmvolunteers",
            "Last Known Event": "Unknown",
            "Last Update": "11/03/2019",
            "People": "N/A",
            "Started": "Unknown",
            "Status": "Unknown",
            "Website": "http://tzmpilipinas.com/",
            "YouTube": "https://www.youtube.com/user/TZMPilipinas",
            "id": "ch-philippines",
            "website.feed.url": "https://tzmpilipinas.com/feed.xml",
            "website.tested": "2020-06-02",
            "website.tested.datetime": "2020-06-02 15:58:17",
            "website.working": "true"
        },
        "ch-poland": {
            "Country": "Poland",
            "Email": "mailto:koordynacja@tzmpolska.org",
            "Facebook": "https://www.facebook.com/tzmpolska/",
            "Last Known Event": "Otwarte Spotkanie Zeitgeist'u \u015al\u0105sk i Zag\u0142\u0119bie",
            "Last Update": "05/02/2019",
            "People": "c.25-30",
            "Started": "11/10/2008",
            "Status": "Active",
            "Website": "www.tzmpolska.org/",
            "YouTube": "https://www.youtube.com/user/TZMPoland",
            "id": "ch-poland",
            "website.tested": "2020-06-02",
            "website.tested.datetime": "2020-06-02 16:01:40",
            "website.working": "false"
        },
        "ch-portugal": {
            "Country": "Portugal",
            "Email": "N/A",
            "Email 2": "mailto:coord@zeitgeistportugal.org",
            "Facebook": "https://www.facebook.com/pg/tzmportugal/",
            "Facebook Group": "https://www.facebook.com/groups/343915479402516/",
            "Last Known Event": "Conversas de Ponta (20/01/2019)",
            "Last Update": "12/03/2019",
            "People": "N/A",
            "Started": "c.2017",
            "Status": "Active",
            "Twitter": "https://twitter.com/tzmportugal",
            "Website": "N/A",
            "Website 2": "http://www.zeitgeistportugal.pt/",
            "YouTube": "https://www.youtube.com/ZeitgeistPortgual",
            "id": "ch-portugal"
        },
        "ch-romania": {
            "Country": "Romania",
            "Email": "mailto:tzmromania@gmail.com",
            "Facebook": "https://www.facebook.com/miscarea.z.romania/",
            "Last Known Event": "Unknown",
            "Last Update": "12/03/2019",
            "People": "N/A",
            "Started": "Unknown",
            "Status": "Inactive",
            "Website": "www.thezeitgeistmovement.ro.org",
            "YouTube": "https://www.youtube.com/user/ZeitgeistRomania",
            "id": "ch-romania",
            "website.tested": "2020-06-02",
            "website.tested.datetime": "2020-06-02 16:01:40",
            "website.working": "false"
        },
        "ch-russia": {
            "Country": "Russia",
            "Email": "mailto:chapter@z-g-m.ru",
            "Facebook": "https://www.facebook.com/russia.tzm/",
            "Facebook Group": "https://www.facebook.com/groups/tzm.russia",
            "Last Known Event": "Unknown",
            "Last Update": "04/04/2019",
            "People": "N/A",
            "Started": "2008",
            "Status": "Active",
            "Vkontakte": "https://vk.com/tzmrussia",
            "Website": "https://z-g-m.ru/",
            "YouTube": "https://www.youtube.com/user/TZMOfficialRussia",
            "id": "ch-russia",
            "website.tested": "2020-06-02",
            "website.tested.datetime": "2020-06-03 11:13:03",
            "website.working": "true"
        },
        "ch-singapore": {
            "Country": "Singapore",
            "Email": "mailto:tzm.sg.coord@gmail.com",
            "Facebook": "https://www.facebook.com/pg/tzmsg",
            "Facebook Group": "https://www.facebook.com/groups/tzmsg",
            "Last Known Event": "Unknown",
            "Last Update": "12/03/2019",
            "People": "N/A",
            "Started": "Unknown",
            "Status": "Unknown",
            "Website": "https://tzmsg.wordpress.com/",
            "YouTube": "https://www.youtube.com/user/TZMSingapore11",
            "id": "ch-singapore",
            "website.feed.url": "https://tzmsg.wordpress.com/feed.xml",
            "website.tested": "2020-06-02",
            "website.tested.datetime": "2020-06-02 15:58:21",
            "website.working": "true"
        },
        "ch-slovakia": {
            "Country": "Slovakia",
            "Email": "admin@zeitgeistmovement.sk (INACTIVE)",
            "Facebook": "https://www.facebook.com/pg/zgmsk/",
            "Last Known Event": "Unknown",
            "Last Update": "11/03/2019",
            "People": "N/A",
            "Started": "2009",
            "Status": "Inactive",
            "Trello": "https://trello.com/c/mbIB1XKL/38-slovakia",
            "Twitter": "https://twitter.com/zgmsk",
            "Website": "https://zeitgeistmovement.sk/",
            "YouTube": "https://www.youtube.com/user/ZeitgeistMovementSK",
            "id": "ch-slovakia",
            "website.tested": "2020-06-02",
            "website.tested.datetime": "2020-06-03 11:13:06",
            "website.working": "true"
        },
        "ch-southafrica": {
            "Country": "South Africa",
            "Email": "tzminfo@www.thezeitgeistmovement.co.za/ (INACTIVE)",
            "Facebook": "https://www.facebook.com/The-Zeitgeist-Movement-South-Africa-158715087500173/",
            "Facebook Group": "https://www.facebook.com/groups/ubuntuguru",
            "Last Known Event": "Unknown",
            "Last Update": "12/03/2019",
            "People": "N/A",
            "Started": "c.2010",
            "Status": "Defunct",
            "Twitter": "https://twitter.com/tzmsa",
            "Website": "http://www.thezeitgeistmovement.co.za/",
            "YouTube": "https://www.youtube.com/user/tzmindia",
            "id": "ch-southafrica",
            "website.tested": "2020-06-02",
            "website.tested.datetime": "2020-06-02 16:01:52",
            "website.working": "false"
        },
        "ch-spain": {
            "Country": "Spain",
            "Email": "mailto:modelo.zeit@gmail.com",
            "Facebook": "https://www.facebook.com/Movimiento-Zeitgeist-Espa\u00f1a-Oficial-165005146861833/",
            "Last Known Event": "Unknown",
            "Last Update": "05/02/2019",
            "People": "N/A",
            "Started": "11/10/2008",
            "Status": "Defunct",
            "Website": "https://zeitgeistciudadreal.blogspot.com/",
            "id": "ch-spain",
            "website.feed.url": "https://zeitgeistciudadreal.blogspot.com/rss.xml",
            "website.tested": "2020-06-02",
            "website.tested.datetime": "2020-06-02 15:58:35",
            "website.working": "true"
        },
        "ch-sweden": {
            "Country": "Sweden",
            "Email": "mailto:stockholmg@thezeitgeistmovement.se",
            "Facebook": "https://www.facebook.com/ZeitgeistrorelsenISverige/",
            "Facebook Group": "https://www.facebook.com/groups/zeitgeiststockholm/",
            "Last Known Event": "TZM Stockholm M\u00f6te 15/12/2018",
            "Last Update": "05/02/2019",
            "People": "c.10",
            "Started": "11/10/2008",
            "Status": "Active",
            "Website": "http://thezeitgeistmovement.se/",
            "YouTube": "https://www.youtube.com/user/tzmse",
            "id": "ch-sweden",
            "website.feed.url": "https://thezeitgeistmovement.se/rss/",
            "website.tested": "2020-06-02",
            "website.tested.datetime": "2020-06-02 15:58:36",
            "website.working": "true"
        },
        "ch-switzerland": {
            "Country": "Switzerland",
            "Email": "N/A",
            "Facebook": "https://www.facebook.com/zeitgeist.switzerland/",
            "Facebook Group": "https://www.facebook.com/groups/188351841207404/",
            "Google+": "https://plus.google.com/communities/108065753679747200278",
            "Last Known Event": "Chapter Treffen (05/2016)",
            "Last Update": "05/02/2019",
            "People": "N/A",
            "Started": "11/10/2008",
            "Status": "Defunct",
            "Website": "http://www.tszm.ch/de",
            "YouTube": "https://www.youtube.com/channel/UCTHn_7Sy3g3Da3AratlfZ2g",
            "id": "ch-switzerland",
            "website.tested": "2020-06-02",
            "website.tested.datetime": "2020-06-02 16:01:53",
            "website.working": "false"
        },
        "ch-taiwan": {
            "Country": "Taiwan",
            "Email": "mailto:pingshyu@gmail.com",
            "Facebook": "https://www.facebook.com/groups/twtzm",
            "Last Known Event": "\u56de\u6b78\u81ea\u7136\u3002\u505a\u81ea\u5df1\uff5e\uff5e\u751f\u614b\u793e\u5340\u5be6\u8e10\u5206\u4eab (2019)",
            "Last Update": "12/03/2019",
            "People": "c.20",
            "Started": "c.2011",
            "Status": "Active",
            "Website": "N/A",
            "id": "ch-taiwan"
        },
        "ch-turkey": {
            "Country": "Turkey",
            "Email": "mailto:tzmturkiye@gmail.com",
            "Facebook": "https://www.facebook.com/tzmturkiye/",
            "Last Known Event": "Unknown",
            "Last Update": "05/02/2019",
            "People": "N/A",
            "Started": "Unknown",
            "Status": "Unknown",
            "Website": "N/A",
            "id": "ch-turkey"
        },
        "ch-uk": {
            "Country": "United Kingdom",
            "Email": "N/A",
            "Email 02": "uk@thezeitgeistmovementuk.com",
            "Facebook": "https://www.facebook.com/TZMUnitedkingdom",
            "Facebook Group": "https://www.facebook.com/groups/TZMLondonChapter/",
            "Last Known Event": "Zeitgeist Day 2019 London (16/03/2019)",
            "Last Update": "25/04/2019",
            "Meetup": "https://www.meetup.com/Zeitgeist-Movement-London/",
            "People": "N/A",
            "Started": "21/03/2011",
            "Status": "Active",
            "Twitter": "https://twitter.com/tzmuk",
            "Website": "N/A",
            "YouTube": "https://www.youtube.com/user/TZMLondon",
            "id": "ch-uk"
        },
        "ch-ukraine": {
            "Country": "Ukraine",
            "Email": "mailto:tzmukraine@gmail.com",
            "Facebook": "https://www.facebook.com/TZMUkraine/",
            "Instagram": "https://www.instagram.com/tzm_ukraine/",
            "Last Known Event": "Zeitgeist Z-Day Lviv 2018 (24/11/2018)",
            "Last Update": "04/02/2019",
            "People": "N/A",
            "Started": "01/07/2018",
            "Status": "Devloping",
            "Twitter": "https://twitter.com/TZMUkraine",
            "VKontakte": "https://vk.com/tzmukraine",
            "Website": "https://www.tzmukraine.com/",
            "YouTube": "https://www.youtube.com/user/TZMUkraine",
            "id": "ch-ukraine",
            "website.tested": "2020-06-02",
            "website.tested.datetime": "2020-06-02 16:01:53",
            "website.working": "false"
        },
        "ch-usa": {
            "Country": "United States",
            "Email": "N/A",
            "Facebook": "https://www.facebook.com/tzmglobal",
            "Instagram": "https://www.instagram.com/tzmglobal/",
            "Last Known Event": "TZM ST. Pete Monthly Meeting (06/01/2019)",
            "Last Update": "05/02/2019",
            "People": "c.100",
            "Soundcloud": "https://soundcloud.com/user-148391635/tracks",
            "Started": "11/10/2008",
            "Status": "Active",
            "Twitter": "https://twitter.com/tzmglobal",
            "Website": "https://www.thezeitgeistmovement.us/",
            "YouTube": "https://www.youtube.com/user/TZMOfficialChannel",
            "id": "ch-usa",
            "website.feed.url": "https://www.thezeitgeistmovement.us/rss/",
            "website.tested": "2020-06-02",
            "website.tested.datetime": "2020-06-02 15:58:44",
            "website.working": "true"
        },
        "pr-gri": {
            "Affiliations": "TZM",
            "Country": "Global",
            "Email": "N/A",
            "Goal(s)": "The goal is to virtually implement an NLRBE in the largest scale possible in a theoretical way",
            "Last Update": "13/03/2019",
            "People": "N/A",
            "Recruiting": "N/A",
            "Started": "c.2012",
            "Status": "Unknown",
            "Website": "http://www.globalredesigninstitute.org/",
            "id": "pr-gri",
            "website.tested": "2020-06-02",
            "website.tested.datetime": "2020-06-02 16:01:53",
            "website.working": "false"
        },
        "pr-tga": {
            "Affiliations": "TZM Canada",
            "Country": "Canada",
            "Email": "N/A",
            "Goal(s)": "Video blogs about a Canadian TZM activist journeying on their motorcycle",
            "Last Update": "13/03/2019",
            "People": "N/A",
            "Recruiting": "N/A",
            "Started": "Unknown",
            "Status": "Defunct",
            "Website": "http://www.tzmthegreatadventure.com/about-jorge",
            "id": "pr-tga",
            "website.tested": "2020-06-02",
            "website.tested.datetime": "2020-06-02 16:01:53",
            "website.working": "false"
        },
        "pr-tzmaquaponics": {
            "Affiliations": "TZM Ukraine",
            "Country": "Ukraine",
            "Email": "N/A",
            "Facebook": "https://www.facebook.com/TZMUkraine/",
            "Goal(s)": "Aquaponic experiments",
            "Last Update": "06/02/2019",
            "People": "10",
            "Recruiting": "Yes",
            "Started": "2017",
            "Status": "Active",
            "Website": "N/A",
            "id": "pr-tzmaquaponics"
        },
        "pr-tzmbp": {
            "Affiliations": "Unknown",
            "Country": "Global",
            "Email": "N/A",
            "Goal(s)": "Awareness on erdicating diseases",
            "Last Update": "13/03/2019",
            "People": "N/A",
            "Recruiting": "N/A",
            "Started": "Unknown",
            "Status": "Unknown",
            "Website": "https://www.tzmboinc.com/",
            "id": "pr-tzmbp",
            "website.tested": "2020-06-02",
            "website.tested.datetime": "2020-06-02 16:01:54",
            "website.working": "false"
        },
        "pr-tzme": {
            "Affiliations": "None",
            "Country": "Global",
            "Email": "N/A",
            "Facebook": "https://www.facebook.com/events/836968083012084//",
            "Goal(s)": "Education courses promoting post-scarcity",
            "Last Update": "06/02/2019",
            "People": "N/A",
            "Recruiting": "N/A",
            "Started": "2015",
            "Status": "Defunct",
            "Website": "http://www.tzmeducation.org/",
            "id": "pr-tzme",
            "website.tested": "2020-06-02",
            "website.tested.datetime": "2020-06-02 16:02:04",
            "website.working": "false"
        },
        "pr-tzmwiki": {
            "Affiliations": "TZM",
            "Country": "Global",
            "Email": "N/A",
            "Goal(s)": "A TZM-Pedia with entries about the movement",
            "Last Update": "13/03/2019",
            "People": "N/A",
            "Recruiting": "N/A",
            "Started": "c.2009",
            "Status": "Defunct",
            "Website": "https://pma420.tzmwiki.org/",
            "id": "pr-tzmwiki",
            "website.tested": "2020-06-02",
            "website.tested.datetime": "2020-06-03 11:13:08",
            "website.working": "true"
        },
        "pr-wia": {
            "Affiliations": "N/A",
            "Country": "Global",
            "Email": "N/A",
            "Facebook": "https://www.facebook.com/Why.I.Advocate.TheZeitgeistMovement/",
            "Goal(s)": "Encouraging a global internet fad of advocating TZM",
            "Last Update": "14/03/2019",
            "People": "N/A (anonymously carried out)",
            "Recruiting": "N/A",
            "Started": "c.2011",
            "Status": "Inactive",
            "Website": "N/A",
            "YouTube Playlist": "https://www.youtube.com/results?search_query=why+I+advocate+zeitgeist&aq=f",
            "id": "pr-wia"
        },
        "pr-zmp": {
            "Affiliations": "Unknown",
            "Country": "Global",
            "Email": "N/A",
            "Goal(s)": "Online, open-source, art/video community database",
            "Last Update": "13/03/2019",
            "Launchpad": "https://launchpad.net/zeitgeist-media-project",
            "People": "N/A",
            "Recruiting": "N/A",
            "Started": "Unknown",
            "Status": "Defunct",
            "Website": "http://zeitgeistmediaproject.com/",
            "id": "pr-zmp",
            "website.tested": "2020-06-02",
            "website.tested.datetime": "2020-06-02 16:02:09",
            "website.working": "false"
        },
        "te-lingteam": {
            "Email": "N/A",
            "Last Update": "06/02/2019",
            "People": "N/A",
            "Recruiting": "Unknown",
            "Started": "c.2009",
            "Status": "Unknown",
            "Type": "Translation",
            "Website": "N/A",
            "id": "te-lingteam"
        },
        "te-opp": {
            "Affiliations": "N/A",
            "Email": "N/A",
            "Facebook": "https://www.facebook.com/OnePlanetProject/",
            "Last Update": "13/03/2019",
            "People": "N/A",
            "Recruiting": "N/A",
            "Started": "c.2012",
            "Status": "Active",
            "Type": "Global collaberation on spreading awareness of TZM around the world",
            "Website": "N/A",
            "id": "te-opp"
        },
        "te-tzmcomteam": {
            "Email": "N/A (Contact via email form on website)",
            "Last Update": "06/02/2019",
            "People": "2",
            "Recruiting": "Yes",
            "Started": "c.2017",
            "Status": "Active",
            "Type": "Q&A Email Assistence",
            "Website": "https://www.thezeitgeistmovement.com/",
            "id": "te-tzmcomteam",
            "website.tested": "2020-06-02",
            "website.tested.datetime": "2020-06-03 11:13:14",
            "website.working": "true"
        },
        "te-tzmdevelopnews": {
            "Affilitations": "TZM Finland",
            "Email": "N/A (Contact via TZM Discord Server or TZM Finland email)",
            "Last Update": "13/03/2019",
            "People": "1",
            "Recruiting": "N/A",
            "Started": "2018",
            "Status": "Active",
            "Type": "Reporting news and development on internal TZM matters",
            "Website": "https://news.tzm.community/",
            "id": "te-tzmdevelopnews",
            "website.feed.url": "https://news.tzm.community/feed.xml",
            "website.tested": "2020-06-02",
            "website.tested.datetime": "2020-06-02 15:59:01",
            "website.working": "true"
        },
        "te-tzmdiscord": {
            "Affiliations": "TZM Finland",
            "Email": "mailto:zeitgeistfinland@gmail.com",
            "Last Update": "13/03/2019",
            "People": "4",
            "Recruiting": "Unknown",
            "Server Address": "https://discordapp.com/invite/ReAqFk4",
            "Started": "2017",
            "Status": "Active",
            "Type": "Administrating and managing official Discord server for TZM",
            "Website": "N/A",
            "id": "te-tzmdiscord"
        },
        "te-tzmgct": {
            "Email": "mailto:info@tzmgct.com",
            "Last Update": "06/02/2019",
            "People": "4",
            "Recruiting": "No",
            "Started": "15/10/2017",
            "Status": "Active",
            "Type": "Troubleshooting & Coordination",
            "Website": "http://www.tzmgct.com/",
            "id": "te-tzmgct",
            "website.tested": "2020-06-02",
            "website.tested.datetime": "2020-06-02 16:02:16",
            "website.working": "false"
        },
        "te-tzmgr": {
            "Affiliations": "N/A",
            "Blog Talk Raido": "http://www.blogtalkradio.com/zmglobal",
            "Email": "N/A",
            "Last Update": "14/03/2019",
            "People": "1",
            "Recruiting": "N/A",
            "Started": "c.2009",
            "Status": "Active",
            "Type": "Podcats",
            "Website": "https://www.thezeitgeistmovement.com/",
            "iTune Store": "https://itunes.apple.com/WebObjects/MZStore.woa/wa/viewPodcast?id=334102952&mt=2&ls=1",
            "id": "te-tzmgr",
            "website.tested": "2020-06-02",
            "website.tested.datetime": "2020-06-03 11:13:19",
            "website.working": "true"
        },
        "te-zeitnews": {
            "Email": "N/A",
            "Facebok": "https://www.facebook.com/ZeitNewsEN/",
            "Last Update": "13/03/2019",
            "People": "N/A",
            "Recruiting": "N/A",
            "Started": "c.2010",
            "Status": "Active",
            "Type": "Publicate news sources relating to TZM's train of thought",
            "Website": "https://www.zeitnews.org",
            "id": "te-zeitnews",
            "website.feed.url": "https://www.zeitnews.org/rss/",
            "website.tested": "2020-06-02",
            "website.tested.datetime": "2020-06-02 15:59:12",
            "website.working": "true"
        },
        "te-zeitnewsde": {
            "Email": "Facebok",
            "Facebok": "https://www.facebook.com/zeitnews.de/",
            "Last Update": "13/03/2019",
            "People": "N/A",
            "Recruiting": "N/A",
            "Started": "c.2010",
            "Status": "Active",
            "Type": "Publicate news sources relating to TZM's train of thought in German",
            "Website": "https://www.zeitnews.de",
            "id": "te-zeitnewsde",
            "website.tested": "2020-06-02",
            "website.tested.datetime": "2020-06-02 16:02:24",
            "website.working": "false"
        }
    }
}